LICENSE
MANIFEST.in
README.md
setup.py
cloud_composer_json_log_formatter/__init__.py
cloud_composer_json_log_formatter/formatter.py
cloud_composer_json_log_formatter.egg-info/PKG-INFO
cloud_composer_json_log_formatter.egg-info/SOURCES.txt
cloud_composer_json_log_formatter.egg-info/dependency_links.txt
cloud_composer_json_log_formatter.egg-info/top_level.txt